[{
    "title": "Zealot",
    "author": "Reza Aslan"
  },
  {
    "title": "God's Century",
    "author": "Monica Duffy Toft, Daniel Philpott, Timothy Samuel Shah"
  },
  {
    "title": "No God But God",
    "author": "Reza Aslan"
  },
  {
    "title": "Siddhartha",
    "author": "Herman Hesse"
  },
  {
    "title": "Holy Bible",
    "author": "Unknown"
  },
  {
    "title": "The Quran",
    "author": "Unknown"
  },
  {
    "title": "Islam: The Essentials",
    "author": "Tariq Ramadan"
  },
  {
    "title": "The Koran: A very short introduction",
    "author": "Michael Cook"
  },
  {
    "title": "The Persian Wars",
    "author": "Herodotus"
  },
  {
    "title": "Mao Tse-tung",
    "author": "Stuart Schram"
  },
  {
    "title": "The Death of a President",
    "author": "William Manchester"
  },
  {
    "title": "Whose Land?",
    "author": "James Parkes"
  },
  {
    "title": "Roman Britain: Pelican History of England 1",
    "author": "I. A. Richmond"
  },
  {
    "title": "Greek and Roman Political Ideas",
    "author": "Melissa Lane"
  },
  {
    "title": "The Early History of Rome",
    "author": "Livy"
  },
  {
    "title": "The History of the Decline and Fall of the Roman Empire",
    "author": "Edward Gibbon"
  },
  {
    "title": "Augustus: The Biography",
    "author": "Jochen Bleicken"
  },
  {
    "title": "The Penguin History of Modern China",
    "author": "Jonathan Fendy"
  },
  {
    "title": "Oppenheimer",
    "author": "Kai Bird & Martin J. Sherwin"
  },
  {
    "title": "Alexander Hamilton",
    "author": "Ron Chernow"
  },
  {
    "title": "The Second World War",
    "author": "John Keegan"
  },
  {
    "title": "Prohibition",
    "author": "Edward Behr"
  },
  {
    "title": "The Oxford History of the Classical World",
    "author": "John Boardman, Jasper Griffin, Oswyn Murray"
  },
  {
    "title": "A History of the Indians of the United States",
    "author": "Angie Debo"
  },
  {
    "title": "Asia's Reckoning",
    "author": "Richard McGregor"
  },
  {
    "title": "Inside the Clinton White House",
    "author": "Russell L. Riley"
  },
  {
    "title": "The Iliad",
    "author": "Homer"
  },
  {
    "title": "The Odyssey",
    "author": "Homer"
  },
  {
    "title": "Fear & Loathing in America",
    "author": "Hunter S. Thompson"
  },
  {
    "title": "The Great Shark Hunt",
    "author": "Hunter S. Thompson"
  },
  {
    "title": "The War of the World",
    "author": "Niall Ferguson"
  },
  {
    "title": "Post-Truth",
    "author": "James Ball"
  },
  {
    "title": "Dark Money",
    "author": "Jane Mayer"
  },
  {
    "title": "The Shock Doctrine",
    "author": "Naomi Klein"
  },
  {
    "title": "Blitzed",
    "author": "Norman Ohler"
  },
  {
    "title": "Evicted",
    "author": "Matthew Desmond"
  },
  {
    "title": "The Autobiography of Malcolm X",
    "author": "Malcolm X"
  },
  {
    "title": "America",
    "author": "Jean Baudrillard"
  },
  {
    "title": "Vocabulary of Politics",
    "author": "T. D. Weldon"
  },
  {
    "title": "The House of Commons at Work",
    "author": "Eric Taylor"
  },
  {
    "title": "Derelict Britain",
    "author": "John Barr"
  },
  {
    "title": "The Intelligent Woman's Guide to Socialism, Capitalism, Sovietism & Fascism",
    "author": "Bernard Shaw"
  },
  {
    "title": "Ain't I A Woman?",
    "author": "bell hooks"
  },
  {
    "title": "Men Explain Things to Me",
    "author": "Rebecca Solnit"
  },
  {
    "title": "The History of White People",
    "author": "Nell Irvin Painter"
  },
  {
    "title": "Culture War? The Myth of a Polarized America",
    "author": "Morris P. Fiorina, Samuel J. Abrams, Jeremy C. Pope"
  },
  {
    "title": "To Be A Machine",
    "author": "Mark O'Connell"
  },
  {
    "title": "No Is Not Enough",
    "author": "Naomi Klein"
  },
  {
    "title": "Hillbilly Elegy: A Memoir of a Family and Culture in Crisis",
    "author": "J. D. Vance"
  },
  {
    "title": "Slow Violence and the Environmentalism of the Poor",
    "author": "Rob Nixon"
  },
  {
    "title": "Sister Outsider",
    "author": "Audre Lorde"
  },
  {
    "title": "We Were Eight Years in Power",
    "author": "Te-Nehisi Coates"
  },
  {
    "title": "Between the World and Me",
    "author": "Te-Nehisi Coates"
  },
  {
    "title": "Against Everything",
    "author": "Mark Grief"
  },
  {
    "title": "Introduction to Philosophy",
    "author": "John Perry & Michael Bratman"
  },
  {
    "title": "Outline of a Theory of Practice",
    "author": "Pierre Boudieu"
  },
  {
    "title": "The Oxford Companion to Philosophy",
    "author": "Ted Honderich"
  },
  {
    "title": "A Thousand Plateaus: Capitalism & Schizophrenia",
    "author": "Gilles Deleuze & Felix Guattari"
  },
  {
    "title": "The Postmodern Condition: A Report on Knowledge",
    "author": "Jean-François Lyotard"
  },
  {
    "title": "History of Western Philosophy",
    "author": "Bertrand Russell"
  },
  {
    "title": "Philosophical Writings",
    "author": "René Descartes"
  },
  {
    "title": "Second Treatise of Government",
    "author": "John Locke"
  },
  {
    "title": "The Republic",
    "author": "Plato"
  },
  {
    "title": "Imagined Communities",
    "author": "Benedict Anderson"
  },
  {
    "title": "Dialectic of Enlightenment",
    "author": "Theodor Adorno & Max Horkheimer"
  },
  {
    "title": "On Violence",
    "author": "Hannah Arendt"
  },
  {
    "title": "The Origins of Totalitarianism",
    "author": "Hannah Arendt"
  },
  {
    "title": "A Singular Modernity",
    "author": "Frederic Jameson"
  },
  {
    "title": "Minima Moralia",
    "author": "Theodor Adorno"
  },
  {
    "title": "On Ideology",
    "author": "Louis Althusser"
  },
  {
    "title": "The Analects",
    "author": "Confucius"
  },
  {
    "title": "On Suicide",
    "author": "Émile Durkheim"
  },
  {
    "title": "The Prince",
    "author": "Niccolò Machiavelli"
  },
  {
    "title": "A Discourse on Inequality",
    "author": "Jean-Jacques Rousseau"
  },
  {
    "title": "The Social Contract",
    "author": "Jean-Jacques Rousseau"
  },
  {
    "title": "Regarding the Pain of Others",
    "author": "Susan Sontag"
  },
  {
    "title": "Leviathan",
    "author": "Thomas Hobbes"
  },
  {
    "title": "The Nichomachean Ethics",
    "author": "Aristotle"
  },
  {
    "title": "The Politics",
    "author": "Aristotle"
  },
  {
    "title": "A Treatise of Human Nature",
    "author": "David Hume"
  },
  {
    "title": "Beyond Good and Evil",
    "author": "Freidrich Nietzsche"
  },
  {
    "title": "Mythologies",
    "author": "Roland Barthes"
  },
  {
    "title": "The Female Eunuch",
    "author": "Germaine Greer"
  },
  {
    "title": "The Symposium",
    "author": "Plato"
  },
  {
    "title": "Meditations",
    "author": "Marcus Aurelius"
  },
  {
    "title": "Common Sense",
    "author": "Thomas Paine"
  },
  {
    "title": "Why I Write",
    "author": "George Orwell"
  },
  {
    "title": "A Tale of a Tub",
    "author": "Jonathan Swift"
  },
  {
    "title": "Philosophy: A very short introduction",
    "author": "Edward Craig"
  },
  {
    "title": "Poststructuralism: A very short introduction",
    "author": "Catherine Belsey"
  },
  {
    "title": "Postmodernism: A very short introduction",
    "author": "Christopher Butler"
  },
  {
    "title": "We Should All Be Feminists",
    "author": "Chimamanda Ngozi Adichie"
  },
  {
    "title": "Introducing Freud",
    "author": "Richard Appignanesi & Oscar Zarate"
  },
  {
    "title": "Introducing Continental Philosophy",
    "author": "Christopher Kul-Want & Piero"
  },
  {
    "title": "Introducing Slavoj Žižek",
    "author": "Christopher Kul-Want & Piero"
  },
  {
    "title": "Welcome to the Desert of the Real",
    "author": "Slavoj Žižek"
  },
  {
    "title": "Modern Physics",
    "author": "G. E. M. Jauncey"
  },
  {
    "title": "First Aid Manual",
    "author": "The UK's Leading First Aid Providers "
  },
  {
    "title": "Gray's Anatomy",
    "author": "Henry Gray"
  },
  {
    "title": "F**ck It Therapy",
    "author": "John C. Parkin"
  },
  {
    "title": "The Body Keeps Score",
    "author": "Bessel Van der Kolk"
  },
  {
    "title": "When Breath Becomes Air",
    "author": "Paul Kalanithi"
  },
  {
    "title": "The Beginning of Infinity",
    "author": "David Deutsch"
  },
  {
    "title": "Proust was a Neuroscientist",
    "author": "Jonah Lehrer"
  },
  {
    "title": "Tubes",
    "author": "Andrew Blun"
  },
  {
    "title": "The Man Who Knew Infinity",
    "author": "Robert Kanigel"
  },
  {
    "title": "Big Bang",
    "author": "Simon Singh"
  },
  {
    "title": "Sapiens",
    "author": "Yuval Noah Harari"
  },
  {
    "title": "The Selfish Gene",
    "author": "Richard Dawkins"
  },
  {
    "title": "The God Delusion",
    "author": "Richard Dawkins"
  },
  {
    "title": "The Stuff of Thought",
    "author": "Steven Pinker"
  },
  {
    "title": "The Language Instinct",
    "author": "Steven Pinker"
  },
  {
    "title": "The Better Angels of Our Nature",
    "author": "Steven Pinker"
  },
  {
    "title": "Ways of Seeing",
    "author": "John Berger"
  },
  {
    "title": "Outliers",
    "author": "Malcolm Gladwell"
  },
  {
    "title": "Chavs",
    "author": "Owen Jones"
  },
  {
    "title": "Freakonomics",
    "author": "Steven D. Levitt & Stephen J. Dubner"
  },
  {
    "title": "Social Class in the 21st Century",
    "author": "Mike Savage"
  },
  {
    "title": "Human Evolution",
    "author": "Robin Dunbar"
  },
  {
    "title": "Economics: The User's Guide",
    "author": "Ha-Joon Chang"
  },
  {
    "title": "Basic Income and How We Can Make It Happen",
    "author": "Guy Standing"
  },
  {
    "title": "The European Union: A Citizen's Guide",
    "author": "Chris Bicketen"
  },
  {
    "title": "Capital in the 21st Century",
    "author": "Thomas Piketty"
  },
  {
    "title": "The Geometry of Type",
    "author": "Stephen Coles"
  },
  {
    "title": "Things I Have Learned",
    "author": "Stefan Sagmeister"
  },
  {
    "title": "Design Systems",
    "author": "Alla Kholmatova"
  },
  {
    "title": "Shady Characters",
    "author": "Keith Houston"
  },
  {
    "title": "Interaction of Color",
    "author": "Josef Albers"
  },
  {
    "title": "Thoughts on Design",
    "author": "Paul Rand"
  },
  {
    "title": "55",
    "author": "Shomet Tomatsu"
  },
  {
    "title": "It's Not How Good You Are, It's How Good You Want To Be",
    "author": "Paul Arden"
  },
  {
    "title": "The Innovators",
    "author": "Walter Isaacson"
  },
  {
    "title": "Accessibility for Everyone",
    "author": "Laura Kalbag"
  },
  {
    "title": "The Lean Startup",
    "author": "Eric Ries"
  },
  {
    "title": "Sprint",
    "author": "Jake Knapp"
  },
  {
    "title": "How Google Works",
    "author": "Eric Schmidt & Jonathan Rosenberg"
  },
  {
    "title": "Creativity Inc.",
    "author": "Eric Catmull"
  },
  {
    "title": "Steve Jobs",
    "author": "Walter Isaacson"
  },
  {
    "title": "Linux in a Nutshell",
    "author": "Ellen Siver"
  },
  {
    "title": "Genius at Play",
    "author": "Siobhan Roberts"
  },
  {
    "title": "Einstein's Greatest Mistake",
    "author": "David Bodanis"
  },
  {
    "title": "Natural Language Understanding",
    "author": "James Allen"
  },
  {
    "title": "Pragmatics and Natural Language Understanding",
    "author": "Georgia M. Green"
  },
  {
    "title": "Formalizing Common Sense",
    "author": "John McCarthy"
  },
  {
    "title": "Countdown to Zero Day",
    "author": "Kim Zetter"
  },
  {
    "title": "How to Create a Mind",
    "author": "Ray Kurzweil"
  },
  {
    "title": "The Art of Computer Programming: Vol 1 - Fundamental Algorithms",
    "author": "Donald E. Knuth"
  },
  {
    "title": "The Art of Computer Programming: Vol 2 - Semi Numerical Algorithms",
    "author": "Donald E. Knuth"
  },
  {
    "title": "The Art of Computer Programming: Vol 3 - Searching and Sorting",
    "author": "Donald E. Knuth"
  },
  {
    "title": "RESTful Web Services",
    "author": "Leonard Richardson & Sam Ruby"
  },
  {
    "title": "A History of Photography",
    "author": "The George Eastman House Collection"
  },
  {
    "title": "Lonely Planet Edinburgh",
    "author": "Neil Wilson"
  },
  {
    "title": "Lonely Planet USA",
    "author": "Regus St Louis"
  },
  {
    "title": "Lonely Planet California",
    "author": "Sarah Benson"
  },
  {
    "title": "Lonely Planet Canada",
    "author": "Karla Zimmerman"
  },
  {
    "title": "Lonely Planet Rome",
    "author": "Abigail Blasi"
  },
  {
    "title": "Lonely Planet Prague & the Czech Republic",
    "author": "Neil Wilson"
  },
  {
    "title": "Lonely Planet London",
    "author": "Peter Dragicevich"
  },
  {
    "title": "Lonely Planet Budapest",
    "author": "Steve Fallon"
  },
  {
    "title": "Lonely Planet Berlin",
    "author": "Andrea Schuelt-Peevers"
  },
  {
    "title": "Lonely Planet Barcelona",
    "author": "Regus St Louis"
  },
  {
    "title": "Lonely Planet Amsterdam",
    "author": "Karla Zimmerman"
  },
  {
    "title": "Underground Overground",
    "author": "Andrew Martin"
  },
  {
    "title": "Notes from a Small Island",
    "author": "Bill Bryson"
  },
  {
    "title": "A Walk in the Woods",
    "author": "Bill Bryson"
  },
  {
    "title": "Neither Here nor There",
    "author": "Bill Bryson"
  },
  {
    "title": "Underworld London",
    "author": "Catharine Arnold"
  },
  {
    "title": "Prisoners of Geography",
    "author": "Tim Marshall"
  },
  {
    "title": "Triumph of the City",
    "author": "Edward Glaser"
  },
  {
    "title": "Happy City",
    "author": "Charles Montgomery"
  },
  {
    "title": "How to Lie With Maps",
    "author": "Mark Monmonier"
  },
  {
    "title": "Shit London",
    "author": "Patrick Dalton"
  },
  {
    "title": "The Very Hungover Caterpillar",
    "author": "Josie Lloyd & Emlyn Rees"
  },
  {
    "title": "Bloom",
    "author": "Estée Lalonde"
  },
  {
    "title": "London: The Information Capital",
    "author": "James Cheshire & Oliver Uberti"
  },
  {
    "title": "London Underground Maps",
    "author": "Claire Dobbin"
  },
  {
    "title": "The Way By Swanns",
    "author": "Marcel Proust"
  },
  {
    "title": "Rebecca",
    "author": "Daphne du Maurier"
  },
  {
    "title": "The Parasites",
    "author": "Daphne du Maurier"
  },
  {
    "title": "My Cousin Rachel",
    "author": "Daphne du Maurier"
  },
  {
    "title": "Herzog",
    "author": "Saul Bellow"
  },
  {
    "title": "Lunar Park",
    "author": "Bret Easton Ellis"
  },
  {
    "title": "American Psycho",
    "author": "Bret Easton Ellis"
  },
  {
    "title": "Ubik",
    "author": "Philip K. Dick"
  },
  {
    "title": "Do Androids Dream Of Sleep?",
    "author": "Philip K. Dick"
  },
  {
    "title": "A Scanner Darkly",
    "author": "Philip K. Dick"
  },
  {
    "title": "The Man in the High Castle",
    "author": "Philip K. Dick"
  },
  {
    "title": "American Psycho",
    "author": "Bret Easton Ellis"
  },
  {
    "title": "The Picture of Dorian Gray",
    "author": "Oscar Wilde"
  },
  {
    "title": "Northanger Abbey and Other Works",
    "author": "Jane Austen"
  },
  {
    "title": "The Age of Innocence",
    "author": "Edith Wharton"
  },
  {
    "title": "American Psycho",
    "author": "Bret Easton Ellis"
  },
  {
    "title": "Silas Marner",
    "author": "George Eliot"
  },
  {
    "title": "The Count of Monte Cristo",
    "author": "Alexandre Dumas"
  },
  {
    "title": "The Name of the Rose",
    "author": "Umberto Eco"
  },
  {
    "title": "In Evil Hour",
    "author": "Gabriel Garcia Marquez"
  },
  {
    "title": "The Autumn of the Patriarch",
    "author": "Gabriel Garcia Marquez"
  },
  {
    "title": "One Hundred Years of Solitude",
    "author": "Gabriel Garcia Marquez"
  },
  {
    "title": "Love In The Time of Cholera",
    "author": "Gabriel Garcia Marquez"
  },
  {
    "title": "Lolita",
    "author": "Vladimir Nabokov"
  },
  {
    "title": "Pale Fire",
    "author": "Vladimir Nabokov"
  },
  {
    "title": "The Book of Laughter and Forgetting",
    "author": "Milan Kundera"
  },
  {
    "title": "The Unbearable Lightness of Being",
    "author": "Milan Kundera"
  },
  {
    "title": "As I Lay Dying",
    "author": "William Faulkner"
  },
  {
    "title": "Brave New World",
    "author": "Aldous Huxley"
  },
  {
    "title": "Point Counter Point",
    "author": "Aldous Huxley"
  },
  {
    "title": "The Exiles Return",
    "author": "Elisabeth de Waal"
  },
  {
    "title": "An Interrupted Life: The Diaries and Letters of Etty Hillesum 1941-43",
    "author": "Etty Hillesum"
  },
  {
    "title": "12 Years A Slave",
    "author": "Solomon Northrup"
  },
  {
    "title": "Tess of the D'Urbervilles",
    "author": "Thomas Hardy"
  },
  {
    "title": "Lady Chatterly's Lover",
    "author": "D. H. Lawrence"
  },
  {
    "title": "Sons and Lovers",
    "author": "D. H. Lawrence"
  },
  {
    "title": "The Hunchback of Notre-Dame",
    "author": "Victor Hugo"
  },
  {
    "title": "Great Expectations",
    "author": "Charles Dickens"
  },
  {
    "title": "Pickwick Papers",
    "author": "Charles Dickens"
  },
  {
    "title": "Nicholas Nickelby",
    "author": "Charles Dickens"
  },
  {
    "title": "Old Curiosity Shop",
    "author": "Charles Dickens"
  },
  {
    "title": "David Copperfield",
    "author": "Charles Dickens"
  },
  {
    "title": "Hard Times",
    "author": "Charles Dickens"
  },
  {
    "title": "Oliver Twist",
    "author": "Charles Dickens"
  },
  {
    "title": "Canterbury Tales",
    "author": "Geoffrey Chaucer"
  },
  {
    "title": "North and South",
    "author": "Elizabeth Gaskell"
  },
  {
    "title": "Frankenstein",
    "author": "Mary Shelley"
  },
  {
    "title": "The Woman in White",
    "author": "Wilkie Collins"
  },
  {
    "title": "Wuthering Heights",
    "author": "Emily Brontë"
  },
  {
    "title": "Emma",
    "author": "Jane Austen"
  },
  {
    "title": "Treasure Island",
    "author": "Robert Louis Stevenson"
  },
  {
    "title": "Notes from Underground and The Double",
    "author": "Fyodor Dostoyevsky"
  },
  {
    "title": "Sir Gawain and the Green Knight",
    "author": "The Pearl Poet"
  },
  {
    "title": "Mrs Dalloway",
    "author": "Virginia Woolf"
  },
  {
    "title": "To The Lighthouse",
    "author": "Virginia Woolf"
  },
  {
    "title": "The Waves",
    "author": "Virginia Woolf"
  },
  {
    "title": "The Good Solider",
    "author": "Ford Madox Ford"
  },
  {
    "title": "The Secret Agent",
    "author": "Joseph Conrad"
  },
  {
    "title": "Gulliver's Travels",
    "author": "Jonathan Swift"
  },
  {
    "title": "Selected Prose",
    "author": "John Donne"
  },
  {
    "title": "Confessions of an English Opium Eater",
    "author": "Thomas de Quincey"
  },
  {
    "title": "To The Lighthouse",
    "author": "Virginia Woolf"
  },
  {
    "title": "To Kill A Mockingbird",
    "author": "Harper Lee"
  },
  {
    "title": "The French Lieutenant's Woman",
    "author": "John Fowles"
  },
  {
    "title": "Catch 22",
    "author": "Joseph Heller"
  },
  {
    "title": "Bridget Jones's Diary",
    "author": "Helen Fielding"
  },
  {
    "title": "Breakfast at Tiffany's",
    "author": "Truman Capote"
  },
  {
    "title": "Watership Downs",
    "author": "Richard Adams"
  },
  {
    "title": "The Beach",
    "author": "Alex Garland"
  },
  {
    "title": "To Sir With Love",
    "author": "E. R. Braithwaite"
  },
  {
    "title": "Dubliners",
    "author": "James Joyce"
  },
  {
    "title": "Crime and Punishment",
    "author": "Fyodor Dostoyevsky"
  },
  {
    "title": "Heart of Darkness",
    "author": "Joseph Conrad"
  },
  {
    "title": "Carrie",
    "author": "Stephen King"
  },
  {
    "title": "Cujo",
    "author": "Stephen King"
  },
  {
    "title": "Pet Semetary",
    "author": "Stephen King"
  },
  {
    "title": "The Shining",
    "author": "Stephen King"
  },
  {
    "title": "Misery",
    "author": "Stephen King"
  },
  {
    "title": "Goes To The Movies",
    "author": "Stephen King"
  },
  {
    "title": "The Bell Jar",
    "author": "Silvia Plath"
  },
  {
    "title": "The Virgin Suicides",
    "author": "Jeffrey Eugenides"
  },
  {
    "title": "The Bloody Chamber",
    "author": "Angela Carter"
  },
  {
    "title": "The Talented Mr Ripley",
    "author": "Patricia Highsmith"
  },
  {
    "title": "The Other Boleyn Girl",
    "author": "Philippa Gregory"
  },
  {
    "title": "The Catcher In The Rye",
    "author": "J. D. Salinger"
  },
  {
    "title": "We Need To Talk About Kevin",
    "author": "Lionel Shriver"
  },
  {
    "title": "HHhH",
    "author": "Laurent Binet"
  },
  {
    "title": "Let The Great World Spin",
    "author": "Colum McCann"
  },
  {
    "title": "The Plot Against America",
    "author": "Philip Roth"
  },
  {
    "title": "American Pastoral",
    "author": "Philip Roth"
  },
  {
    "title": "The War of Don Emmanuel's Nether Parts",
    "author": "Louis de Bernieres"
  },
  {
    "title": "The Troublesome Offspring of Cardinal Guzman",
    "author": "Louis de Bernieres"
  },
  {
    "title": "Captain Corelli's Mandolin",
    "author": "Louis de Bernieres"
  },
  {
    "title": "Birds Without Wings",
    "author": "Louis de Bernieres"
  },
  {
    "title": "Red Dog",
    "author": "Louis de Bernieres"
  },
  {
    "title": "Four Plays",
    "author": "Christopher Marlowe"
  },
  {
    "title": "Bel-Ami",
    "author": "Guy de Maupassant"
  },
  {
    "title": "Oh What A Lovely War",
    "author": "Joan Littlewood"
  },
  {
    "title": "The Importance of Being Earnest",
    "author": "Oscar Wilde"
  },
  {
    "title": "King Lear",
    "author": "William Shakespeare"
  },
  {
    "title": "The Winter's Tale",
    "author": "William Shakespeare"
  },
  {
    "title": "Julias Caesar",
    "author": "William Shakespeare"
  },
  {
    "title": "Coriolanus",
    "author": "William Shakespeare"
  },
  {
    "title": "Henry V",
    "author": "William Shakespeare"
  },
  {
    "title": "Julias Caesar",
    "author": "William Shakespeare"
  },
  {
    "title": "As You Like It",
    "author": "William Shakespeare"
  },
  {
    "title": "The Taming of the Shrew",
    "author": "William Shakespeare"
  },
  {
    "title": "Beowulf",
    "author": "Unknown"
  },
  {
    "title": "Paradise Lost",
    "author": "John Milton"
  },
  {
    "title": "A Doll's House",
    "author": "Henrik Ibsen"
  },
  {
    "title": "The Oxford Book of English Short Stories",
    "author": ""
  },
  {
    "title": "London Stories",
    "author": ""
  },
  {
    "title": "Endgame",
    "author": "Samuel Beckett"
  },
  {
    "title": "The Waste Land",
    "author": "T. S. Eliot"
  },
  {
    "title": "The Testament of Cressid & Seven Fables",
    "author": "Robert Henryson"
  },
  {
    "title": "Collected Poems",
    "author": "Philip Larkin"
  },
  {
    "title": "Selected Poems",
    "author": "Sylvia Plath"
  },
  {
    "title": "Ariel",
    "author": "Sylvia Plath"
  },
  {
    "title": "Crow",
    "author": "Ted Hughes"
  },
  {
    "title": "The Penguin Book of First World War Poetry",
    "author": ""
  },
  {
    "title": "Selected Poems",
    "author": "W. H. Auden"
  },
  {
    "title": "Milk and Honey",
    "author": "Rupi Kaur"
  },
  {
    "title": "Selected Poetry",
    "author": "Alexander Pope"
  },
  {
    "title": "Collected Poems",
    "author": "John Donne"
  },
  {
    "title": "Scars Upon My Heart",
    "author": "Catherine Reilly"
  },
  {
    "title": "The Faber Book of Modern Verse",
    "author": ""
  },
  {
    "title": "100 Selected Poems",
    "author": "E. E. Cummings"
  },
  {
    "title": "Complete Poems of Robert Frost",
    "author": "Robert Frost"
  },
  {
    "title": "The Penguin Book of First World War Poetry",
    "author": ""
  },
  {
    "title": "Treasury of World Masterpieces: Oscar Wilde",
    "author": "Oscar Wilde"
  },
  {
    "title": "The Seagull",
    "author": "Anton Chekhov"
  },
  {
    "title": "Hero and Leander",
    "author": "Christopher Marlowe"
  },
  {
    "title": "Richard The Second",
    "author": "William Shakespeare"
  },
  {
    "title": "Hero and Leander",
    "author": "Christopher Marlowe"
  },
  {
    "title": "A Heartbreaking Work of Staggering Genius",
    "author": "Dave Eggers"
  },
  {
    "title": "Infinite Jest",
    "author": "David Foster Wallace"
  },
  {
    "title": "Cloud Atlas",
    "author": "David Mitchell"
  },
  {
    "title": "Do Not Say We Have Nothing",
    "author": "Madeliene Thien"
  },
  {
    "title": "Wild Swans",
    "author": "Jung Chang"
  },
  {
    "title": "Gilead",
    "author": "Marilynne Robinson"
  },
  {
    "title": "The Goldfinch",
    "author": "Donna Tartt"
  },
  {
    "title": "Falling Man",
    "author": "Don Delillo"
  },
  {
    "title": "Sputnik Sweetheart",
    "author": "Haruki Murakami"
  },
  {
    "title": "Norwegian Wood",
    "author": "Haruki Murakami"
  },
  {
    "title": "Dance Dance Dance",
    "author": "Haruki Murakami"
  },
  {
    "title": "After The Quake",
    "author": "Haruki Murakami"
  },
  {
    "title": "Colorless Tsukuru Tazaki and His Years of Pilgrimage",
    "author": "Haruki Murakami"
  },
  {
    "title": "The Wind-Up Bird Chronicle",
    "author": "Haruki Murakami"
  },
  {
    "title": "Kafka On The Shore",
    "author": "Haruki Murakami"
  },
  {
    "title": "Desire",
    "author": "Haruki Murakami"
  },
  {
    "title": "1Q84",
    "author": "Haruki Murakami"
  },
  {
    "title": "The Answers",
    "author": "Catherine Lacey"
  },
  {
    "title": "The Sellout",
    "author": "Paul Beatty"
  },
  {
    "title": "Birdsong",
    "author": "Sebastian Faulks"
  },
  {
    "title": "Atonement",
    "author": "Sebastian Faulks"
  },
  {
    "title": "The Power",
    "author": "Naomi Alderman"
  },
  {
    "title": "Autumn",
    "author": "Ali Smith"
  },
  {
    "title": "The Accidental",
    "author": "Ali Smith"
  },
  {
    "title": "The Past",
    "author": "Tessa Hadley"
  },
  {
    "title": "The Essex Serpent",
    "author": "Sarah Perry"
  },
  {
    "title": "The First Bad Man",
    "author": "Miranda July"
  },
  {
    "title": "I Love Dick",
    "author": "Chris Kraus"
  },
  {
    "title": "Gone Girl",
    "author": "Gillian Flynn"
  },
  {
    "title": "The Reader",
    "author": "Berhard Schlink"
  },
  {
    "title": "The Martian",
    "author": "Andy Weir"
  },
  {
    "title": "Trainspotting",
    "author": "Irvine Welsh"
  },
  {
    "title": "The Vegetarian",
    "author": "Han King"
  },
  {
    "title": "We Are All Completely Beside Ourselves",
    "author": "Karen Joy Fowler"
  },
  {
    "title": "Black Girl White Girl",
    "author": "Joyce Carol Oates"
  },
  {
    "title": "Slumdog Millionaire",
    "author": "Vikas Swarup"
  },
  {
    "title": "The Sense of an Ending",
    "author": "Julian Barnes"
  },
  {
    "title": "The Brief Wondrous Life of Oscar Wao",
    "author": "Junot Diaz"
  },
  {
    "title": "Postcards From The Edge",
    "author": "Carrie Fisher"
  },
  {
    "title": "The Color Purple",
    "author": "Alice Walker"
  },
  {
    "title": "White Teeth",
    "author": "Zadie Smith"
  },
  {
    "title": "NW",
    "author": "Zadie Smith"
  },
  {
    "title": "Swing Time",
    "author": "Zadie Smith"
  },
  {
    "title": "Brick Lane",
    "author": "Monica Ali"
  },
  {
    "title": "Americanah",
    "author": "Chimamanda Ngozi Adichie"
  },
  {
    "title": "The Muse",
    "author": "Jessie Burton"
  },
  {
    "title": "The Miniaturist",
    "author": "Jessie Burton"
  },
  {
    "title": "The Norton Anthology of Theory & Criticism",
    "author": ""
  },
  {
    "title": "The Norton Anthology of Poetry",
    "author": ""
  },
  {
    "title": "Tragedy: A Short Introduction",
    "author": "Rebecca Bushnell"
  },
  {
    "title": "501 French Verbs",
    "author": ""
  },
  {
    "title": "Paul Humberstone",
    "author": "Paul Humberstone"
  },
  {
    "title": "L'Etranger",
    "author": "Albert Camus"
  },
  {
    "title": "A Happy Death",
    "author": "Albert Camus"
  },
  {
    "title": "Premiers Dialogues",
    "author": "Platon"
  },
  {
    "title": "La Chute",
    "author": "Albert Camus"
  },
  {
    "title": "Les vacances du petit Nicolas",
    "author": "René Goscinny and Jean-Jacques Sempé"
  },
  {
    "title": "Sur la plage de Chesil",
    "author": "Ian McEwan"
  },
  {
    "title": "Push",
    "author": "Sapphire"
  },
  {
    "title": "L'humour anglo-saxon",
    "author": "Jean Autret"
  },
  {
    "title": "Sur la plage de Chesil",
    "author": "Ian McEwan"
  },
  {
    "title": "Eats, Shoots & Leaves",
    "author": "Lynn Truss"
  },
  {
    "title": "Classical Literature",
    "author": "Richard Jenkyns"
  },
  {
    "title": "The Uncommon Reader",
    "author": "Alan Bennett"
  },
  {
    "title": "The Pelican Guide To English Literature 5: From Blake To Byron",
    "author": ""
  },
  {
    "title": "Oxford Dictionary of Economics",
    "author": ""
  },
  {
    "title": "The Guardian Book of English Language",
    "author": ""
  },
  {
    "title": "The Penguin Dictionary of Clichés",
    "author": ""
  },
  {
    "title": "The Penguin Dictonary of Usage & Abusage",
    "author": ""
  },
  {
    "title": "The Penguin Dictionary of Proverbs",
    "author": ""
  },
  {
    "title": "The Penguin Dictionary of Mind The Caffe",
    "author": ""
  },
  {
    "title": "The Penguin Dictionary of Modern Humorous Quotations",
    "author": ""
  },
  {
    "title": "The Penguin Dictionary of Literary Terms & Literary Theory",
    "author": ""
  },
  {
    "title": "Trimalchio",
    "author": "F. Scott Fitzgerald"
  },
  {
    "title": "The Last Tycoon",
    "author": "F. Scott Fitzgerald"
  },
  {
    "title": "Tales of the Jazz Age",
    "author": "F. Scott Fitzgerald"
  },
  {
    "title": "The Great Gatsby",
    "author": "F. Scott Fitzgerald"
  },
  {
    "title": "Flappers and Philosophers: The Collected Short Stories",
    "author": "F. Scott Fitzgerald"
  },
  {
    "title": "The Beautiful and Damned",
    "author": "F. Scott Fitzgerald"
  },
  {
    "title": "Tender is the Night",
    "author": "F. Scott Fitzgerald"
  },
  {
    "title": "Nausea",
    "author": "Jean-Paul Sartre"
  },
  {
    "title": "In Cold Blood",
    "author": "Truman Capote"
  },
  {
    "title": "Fictions",
    "author": "Jorge Luis Borges"
  },
  {
    "title": "Voyage in the Dark",
    "author": "Jean Rhys"
  },
  {
    "title": "One Flew Over The Cuckoo's Nest",
    "author": "Ken Kesey"
  },
  {
    "title": "Ragtime",
    "author": "E. L. Doctorow"
  },
  {
    "title": "Cat's Cradle",
    "author": "Kurt Vonnegut"
  },
  {
    "title": "Journey's End",
    "author": "R. C. Sherriff"
  },
  {
    "title": "Junky",
    "author": "William S. Burroughs"
  },
  {
    "title": "The Rebel",
    "author": "Albert Camus"
  },
  {
    "title": "Goodbye To All That",
    "author": "Robert Graves"
  },
  {
    "title": "It Can't Happen Here",
    "author": "Sinclair Lewis"
  },
  {
    "title": "The Castle",
    "author": "Franz Kafka"
  },
  {
    "title": "The Trial",
    "author": "Franz Kafka"
  },
  {
    "title": "Selected Short Stories",
    "author": "Franz Kafka"
  },
  {
    "title": "Gravity's Rainbow",
    "author": "Thomas Pynchon"
  },
  {
    "title": "Swing Hammer Swing",
    "author": "Jeff Torrington"
  },
  {
    "title": "Beloved",
    "author": "Toni Morrison"
  },
  {
    "title": "The Heat of the Day",
    "author": "Elizabeth Bowen"
  },
  {
    "title": "All Quiet On The Western Front",
    "author": "Erich Maria Remarque"
  },
  {
    "title": "Jane Eyre",
    "author": "Charlotte Brontë"
  },
  {
    "title": "Men Without Women",
    "author": "Ernest Hemingway"
  },
  {
    "title": "For Whom The Bell Tolls",
    "author": "Ernest Hemingway"
  },
  {
    "title": "True At First Light",
    "author": "Ernest Hemingway"
  },
  {
    "title": "A Farewell To Arms",
    "author": "Ernest Hemingway"
  },
  {
    "title": "A Moveable Feast",
    "author": "Ernest Hemingway"
  },
  {
    "title": "Fiesta: The Sun Also Rises",
    "author": "Ernest Hemingway"
  },
  {
    "title": "Death in the Afternoon",
    "author": "Ernest Hemingway"
  },
  {
    "title": "By-line: Selected Journalism",
    "author": "Ernest Hemingway"
  },
  {
    "title": "Death in the Afternoon",
    "author": "Ernest Hemingway"
  },
  {
    "title": "The Girls",
    "author": "Emma Cline"
  },
  {
    "title": "The Girl on the Train",
    "author": "Paula Hawkins"
  },
  {
    "title": "The Underground Railroad",
    "author": "Colson Whitehead"
  },
  {
    "title": "The Wangs vs. The World",
    "author": "Jade Chang"
  },
  {
    "title": "Us",
    "author": "David Nicholls"
  },
  {
    "title": "One Day",
    "author": "David Nicholls"
  },
  {
    "title": "The Understudy",
    "author": "David Nicholls"
  },
  {
    "title": "Starter for Ten",
    "author": "David Nicholls"
  },
  {
    "title": "Behind the Beautiful Forevers",
    "author": "Katherine Boo"
  },
  {
    "title": "Oryx and Crake",
    "author": "Margaret Atwood"
  },
  {
    "title": "The Year of the Flood",
    "author": "Margaret Atwood"
  },
  {
    "title": "Maddaddam",
    "author": "Margaret Atwood"
  },
  {
    "title": "The Blind Assassin",
    "author": "Margaret Atwood"
  },
  {
    "title": "The Edible Woman",
    "author": "Margaret Atwood"
  },
  {
    "title": "Cat's Eye",
    "author": "Margaret Atwood"
  },
  {
    "title": "Alias Grace",
    "author": "Margaret Atwood"
  },
  {
    "title": "The Heart Goes Last",
    "author": "Margaret Atwood"
  },
  {
    "title": "Moral Disorder",
    "author": "Margaret Atwood"
  },
  {
    "title": "Surfacing",
    "author": "Margaret Atwood"
  },
  {
    "title": "Life Before Man",
    "author": "Margaret Atwood"
  },
  {
    "title": "Never Let Me Go",
    "author": "Kazuo Ishiguro"
  },
  {
    "title": "The Remains of the Day",
    "author": "Kazuo Ishiguro"
  },
  {
    "title": "The Lord of the Rings",
    "author": "J. R. R. Tolkien"
  },
  {
    "title": "The Silmarillion",
    "author": "J. R. R. Tolkien"
  },
  {
    "title": "The Hobbit",
    "author": "J. R. R. Tolkien"
  },
  {
    "title": "The Tolkien Reader",
    "author": "J. R. R. Tolkien"
  },
  {
    "title": "Ethel and Earnest",
    "author": "Raymond Briggs"
  },
  {
    "title": "The Doomspell",
    "author": "Cliff McNish"
  },
  {
    "title": "Mondays are Red",
    "author": "Nicola Morgan"
  },
  {
    "title": "The Book Thief",
    "author": "Marcus Zusak"
  },
  {
    "title": "Strange Meeting",
    "author": "Susan Hill"
  },
  {
    "title": "Grief is the Thing with Feathers",
    "author": "Max Porter"
  },
  {
    "title": "Lord of the Flies",
    "author": "William Golding"
  },
  {
    "title": "And the Mountains Echoed",
    "author": "Khaled Hosseini"
  },
  {
    "title": "A Thousand Splendid Suns",
    "author": "Khaled Hosseini"
  },
  {
    "title": "The Curious Incident of the Dog in the Night Time",
    "author": "Mark Haddon"
  },
  {
    "title": "Life of Pi",
    "author": "Yann Martel"
  },
  {
    "title": "Room",
    "author": "Emma Donoghue"
  },
  {
    "title": "The Lovely Bones",
    "author": "Alice Sebold"
  },
  {
    "title": "A Game of Thrones",
    "author": "George R. R. Martin"
  },
  {
    "title": "A Clash of Kings",
    "author": "George R. R. Martin"
  },
  {
    "title": "A Storm of Swords: Steel and Snow",
    "author": "George R. R. Martin"
  },
  {
    "title": "A Storm of Swords: Blood and Gold",
    "author": "George R. R. Martin"
  },
  {
    "title": "A Feast for Crows",
    "author": "George R. R. Martin"
  },
  {
    "title": "A Dance with Dragons: Dreams and Dust",
    "author": "George R. R. Martin"
  },
  {
    "title": "A Dance with Dragons: After The Feast",
    "author": "George R. R. Martin"
  },
  {
    "title": "Quidditch Through the Ages",
    "author": "J. K. Rowling"
  },
  {
    "title": "Harry Potter and the Philosopher's Stone",
    "author": "J. K. Rowling"
  },
  {
    "title": "Harry Potter and the Chamber of Secrets",
    "author": "J. K. Rowling"
  },
  {
    "title": "Harry Potter and the Prisoner of Azkaban",
    "author": "J. K. Rowling"
  },
  {
    "title": "Harry Potter and the Goblet of Fire",
    "author": "J. K. Rowling"
  },
  {
    "title": "Harry Potter and the Order of the Phoenix",
    "author": "J. K. Rowling"
  },
  {
    "title": "Harry Potter and the Half-Blood Prince",
    "author": "J. K. Rowling"
  },
  {
    "title": "Harry Potter and the Deathly Hallows",
    "author": "J. K. Rowling"
  },
  {
    "title": "Skin and Other Stories",
    "author": "Roald Dahl"
  },
  {
    "title": "Cruelty",
    "author": "Roald Dahl"
  },
  {
    "title": "Deception",
    "author": "Roald Dahl"
  },
  {
    "title": "Madness",
    "author": "Roald Dahl"
  },
  {
    "title": "Lust",
    "author": "Roald Dahl"
  },
  {
    "title": "Asterios Polyp",
    "author": "David Mazzucchelli"
  },
  {
    "title": "Watchmen",
    "author": "Alan Moore"
  },
  {
    "title": "V for Vendetta",
    "author": "Alan Moore"
  },
  {
    "title": "Habibi",
    "author": "Craig Thompson"
  },
  {
    "title": "Blankets",
    "author": "Craig Thompson"
  },
  {
    "title": "Persepolis 2",
    "author": "Marjane Satrapi"
  },
  {
    "title": "Fingerprints",
    "author": "Will Dinski"
  },
  {
    "title": "The Twits",
    "author": "Roald Dahl"
  },
  {
    "title": "Charlie and the Chocolate Factory",
    "author": "Roald Dahl"
  },
  {
    "title": "Charlie and the Great Glass Elevator",
    "author": "Roald Dahl"
  },
  {
    "title": "The Giraffe and the Pelly and Me",
    "author": "Roald Dahl"
  },
  {
    "title": "The Witches",
    "author": "Roald Dahl"
  },
  {
    "title": "The Magic Finger",
    "author": "Roald Dahl"
  },
  {
    "title": "James and the Giant Peach",
    "author": "Roald Dahl"
  },
  {
    "title": "The BFG",
    "author": "Roald Dahl"
  },
  {
    "title": "Nib and Ink",
    "author": "Chiara Perano"
  },
  {
    "title": "Mad Men: The End of an Era",
    "author": ""
  },
  {
    "title": "The Gigantic Beard that was Evil",
    "author": "Stephen Collins"
  },
  {
    "title": "The World of Ice and Fire",
    "author": "George R. R. Martin"
  },
  {
    "title": "Romeo & Juliet",
    "author": "William Shakespeare"
  },
  {
    "title": "A Brief History of Seven Killings",
    "author": "Marlon James"
  },
  {
    "title": "The Fall of Icarus",
    "author": "Ovid"
  },
  {
    "title": "Socrates' Defence",
    "author": "Plato"
  },
  {
    "title": "Trimalchio's Feast",
    "author": "Petronius"
  },
  {
    "title": "How to Read London",
    "author": "Chris Rogers"
  },
  {
    "title": "Comprendre L'Architecture",
    "author": "Carol Davidson Cragow"
  },
  {
    "title": "How to Read Towns and Cities",
    "author": "Jonathan Glancey"
  },
  {
    "title": "The 7th Function of Language",
    "author": "Laurent Binet"
  },
  {
    "title": "The Butchering Art",
    "author": "Lindsey Fitzharris"
  },
  {
    "title": "What You Did Not Tell",
    "author": "Mark Mazower"
  },
  {
    "title": "Democracy and Its Crisis",
    "author": "A. C. Grayling"
  },
  {
    "title": "The Water Will Come",
    "author": "Jeff Godell"
  },
  {
    "title": "Hannibal",
    "author": "Livy"
  },
  {
    "title": "The Frogs",
    "author": "Aristophanes"
  },
  {
    "title": "Come Close",
    "author": "Sappho"
  },
  {
    "title": "Typhoon",
    "author": "Joseph Conrad"
  },
  {
    "title": "My Dearest Father",
    "author": "Wolfgang Amadeus Mozart"
  },
  {
    "title": "Those Barren Leaves",
    "author": "Aldous Huxley"
  },
  {
    "title": "French Architecture",
    "author": "Pierre Lavedan"
  },
  {
    "title": "Florence Nightingale",
    "author": "Cecil Woodham-Smith"
  },
  {
    "title": "Music At Night",
    "author": "Aldous Huxley"
  },
  {
    "title": "The English Language",
    "author": "Robert Burchfield"
  },
  {
    "title": "In Defense of Lost Causes",
    "author": "Slavoj Zizek"
  },
  {
    "title": "The System of Objects",
    "author": "Jean Baudrillard"
  },
  {
    "title": "Critique of Instrumental Reason",
    "author": "Max Horkheimer"
  },
  {
    "title": "A Study On Authority",
    "author": "Herbert Marcuse"
  },
  {
    "title": "The Three-Body Problem",
    "author": "Cixin Liu"
  },
  {
    "title": "The Handmaid's Tale",
    "author": "Margaret Atwood"
  },
  {
    "title": "The Stories of Ray Bradbury",
    "author": "Ray Bradbury"
  },
  {
    "title": "Poems and Prophecies",
    "author": "William Blake"
  },
  {
    "title": "What Happened",
    "author": "Hillary Rodham Clinton"
  },
  {
    "title": "Battle Cry of Freedom",
    "author": "James M. McPherson"
  },
  {
    "title": "A Treatise upon the Law, Privileges, Proceedings and Usage of Parliament",
    "author": "Erskine May"
  },
  {
    "title": "Thus Spoke Zarathustra",
    "author": "Friedrich Nietzsche"
  },
  {
    "title": "Beyond Respectability: The Intellectual Thought of Race Women",
    "author": "Brittney C. Cooper"
  },
  {
    "title": "The Old Man and The Sea",
    "author": "Ernest Hemingway"
  },
  {
    "title": "Official Scrabble Words",
    "author": ""
  },
  {
    "title": "Lonely Planet Copenhagen",
    "author": "Christian Bonetto"
  },
  {
    "title": "Queen Victoria: 1819 - 1901",
    "author": "R. R. Holmes"
  },
  {
    "title": "Stalin",
    "author": "Nikolaus Basseches"
  },
  {
    "title": "Frost/Nixton",
    "author": "David Frost"
  },
  {
    "title": "You Tarzan: Masculinity, Movies and Men",
    "author": "Pat Kirkham and Janet Thumin"
  },
  {
    "title": "The Mayor of Casterbridge",
    "author": "Thomas Hardy"
  },
  {
    "title": "The Theatre of the Absurd",
    "author": "Martin Esslin"
  },
  {
    "title": "The God of Small Things",
    "author": "Arundhati Roy"
  },
  {
    "title": "Fear and Trembling",
    "author": "Soren Kierkegaard"
  },
  {
    "title": "The First Forty-Nine Stories",
    "author": "Ernest Hemingway"
  },
  {
    "title": "The Informers",
    "author": "Bret Easton Ellis"
  },
  {
    "title": "Three Plays",
    "author": "Anton Tchekov"
  },
  {
    "title": "Harry Potter: A History of Magic",
    "author": ""
  },
  {
    "title": "Ruling The Void",
    "author": "Peter Mair"
  },
  {
    "title": "Environmental Protection",
    "author": "Pamela Hill"
  },
  {
    "title": "The Story of Life",
    "author": "Chris (Simpsons Artist)"
  },
  {
    "title": "Feed Me Vegan",
    "author": "Lucy Watson"
  },
  {
    "title": "Who Really Runs Britain?",
    "author": "Alan White"
  },
  {
    "title": "The New Spirit of Capitalism",
    "author": "Luc Boltanski and Eve Chiapello"
  },
  {
    "title": "Unexpected Politics",
    "author": "Emily Apter"
  },
  {
    "title": "Keep It Vegan",
    "author": "Aine Carlin"
  },
  {
    "title": "The Rule of Metaphor",
    "author": "Paul Ricoeur"
  },
  {
    "title": "Conjectures and Refutations",
    "author": "Karl Popper"
  },
  {
    "title": "The Penguin Poets: Keats",
    "author": "Ed. J. E. Morpurgo"
  },
  {
    "title": "Plays Pleasant",
    "author": "Bernard Shaw"
  },
  {
    "title": "Poetics",
    "author": "Aristotle"
  },
  {
    "title": "The Kite Runner",
    "author": "Khaled Hosseini"
  },
  {
    "title": "The Problem of Knowledge",
    "author": "A. J. Ayer"
  },
  {
    "title": "Aid as Imperialism",
    "author": "Teresa Hayter"
  },
  {
    "title": "The Communist Manifesto",
    "author": "Karl Marx and Friedrich Engels"
  },
  {
    "title": "Where Angels Fear To Tread",
    "author": "Where Angels Fear To Tread"
  },
  {
    "title": "Stoner: A Novel",
    "author": "John Williams"
  },
  {
    "title": "On The Road",
    "author": "Jack Kerouac"
  },
  {
    "title": "The Woman in Black",
    "author": "Susann Hill"
  },
  {
    "title": "Carol",
    "author": "Patricia Highsmith"
  },
  {
    "title": "How To Be Both",
    "author": "Ali Smith"
  },
  {
    "title": "Hot Milk",
    "author": "Deborah Levy"
  },
  {
    "title": "Martin Luther",
    "author": "Eric Metaxas"
  },
  {
    "title": "Built",
    "author": "Roma Agrawal"
  },
  {
    "title": "Nutshell",
    "author": "Ian McEwan"
  },
  {
    "title": "Technically Wrong: Sexist Apps, Biased Algorithms, and other tales of toxic tech",
    "author": "Sara Wachter-Boettcher"
  },
  {
    "title": "The People v. O.J. Simpson",
    "author": "Jeffrey Toobin"
  },
  {
    "title": "The Ladybird Book of the New You",
    "author": ""
  },
  {
    "title": "Kidnapped",
    "author": "Olaudah Equiano"
  },
  {
    "title": "Circe and the Cyclops",
    "author": "Homer"
  },
  {
    "title": "Anthem for Dommed Youth",
    "author": "Wilfred Owen"
  },
  {
    "title": "Gooseberries",
    "author": "Anton Chekhov"
  },
  {
    "title": "Travels in the Land of Serpents and Pearls",
    "author": "Marco Polo"
  },
  {
    "title": "Jason and Medusa",
    "author": "Apollonius of Rhodes"
  },
  {
    "title": "The Nin of Murano",
    "author": "Giacomo Casanova"
  },
  {
    "title": "The Yellow Book",
    "author": "Various"
  },
  {
    "title": "The Dolphins, the Whales and the Gudgeon",
    "author": "Aesop"
  },
  {
    "title": "Macbeth",
    "author": "William Shakespeare"
  },
  {
    "title": "Dreams From My Father",
    "author": "Barack Obama"
  },
  {
    "title": "A Brief History of Time",
    "author": "Stephen Hawking"
  },
  {
    "title": "Plays Unpleasant",
    "author": "Bernard Shaw"
  },
  {
    "title": "The Caliphate",
    "author": "Hugh Kennedy"
  },
  {
    "title": "The Essays of Francis Bacon",
    "author": "Francis Bacon"
  },
  {
    "title": "Hagseed",
    "author": "Margaret Atwood"
  },
  {
    "title": "Exit West",
    "author": "Mohsin Hamid"
  },
  {
    "title": "London's Underground Suburbs",
    "author": "Dennis Edwards and Ron Pigram"
  },
  {
    "title": "The Great Economists",
    "author": "Linda Yueh"
  },
  {
    "title": "Private Island",
    "author": "James Meek"
  },
  {
    "title": "The Oresteian Trilogy",
    "author": "Aeschylus"
  },
  {
    "title": "The Annals of Imperial Rome",
    "author": "Tacitus"
  },
  {
    "title": "Vanity Fair",
    "author": "William Thackeray"
  },
  {
    "title": "The Divine Comedy 1: Hell",
    "author": "Dante Alighieri"
  },
  {
    "title": "The Frogs and Other Plays",
    "author": "Aristophanes"
  },
  {
    "title": "Down and Out in Paris and London",
    "author": "George Orwell"
  },
  {
    "title": "Homage to Catalonia",
    "author": "George Orwell"
  },
  {
    "title": "Half of a Yellow Sun",
    "author": "Chimamanda Ngozi Adichie"
  },
  {
    "title": "Tony & Susan",
    "author": "Austin Wright"
  },
  {
    "title": "Yes Please",
    "author": "Amy Poehler"
  },
  {
    "title": "Frenchman's Creek",
    "author": "Daphne du Maurier"
  },
  {
    "title": "The Bees",
    "author": "Laline Paull"
  },
  {
    "title": "Revolutionary Road",
    "author": "Richard Yates"
  },
  {
    "title": "A Little Life",
    "author": "Hanya Yanagihara"
  },
  {
    "title": "Eat Up!",
    "author": "Ruby Tandoh"
  },
  {
    "title": "The Oresteia",
    "author": "Aeschylus"
  },
  {
    "title": "The Outline of History Vol. 1",
    "author": "H.G. Wells"
  },
  {
    "title": "The Outline of History Vol. 2",
    "author": "H.G. Wells"
  },
  {
    "title": "Why I'm No Longer Talking To White People About Race",
    "author": "Reni Eddo-Lodge"
  },
  {
    "title": "The Road to Wigan Pier",
    "author": "George Orwell"
  }
]
